dimensigon/__init__.py
dimensigon/__main__.py
dimensigon/bootstrap.py
dimensigon/core.py
dimensigon/db.py
dimensigon/defaults.py
dimensigon/exceptions.py
dimensigon/domain/__init__.py
dimensigon/domain/exceptions.py
dimensigon/domain/locker_memory.py
dimensigon/domain/entities/__init__.py
dimensigon/domain/entities/action_template.py
dimensigon/domain/entities/base.py
dimensigon/domain/entities/bootstrap.py
dimensigon/domain/entities/catalog.py
dimensigon/domain/entities/dimension.py
dimensigon/domain/entities/execution.py
dimensigon/domain/entities/file.py
dimensigon/domain/entities/gate.py
dimensigon/domain/entities/locker.py
dimensigon/domain/entities/log.py
dimensigon/domain/entities/orchestration.py
dimensigon/domain/entities/parameter.py
dimensigon/domain/entities/route.py
dimensigon/domain/entities/schema_changes.py
dimensigon/domain/entities/server.py
dimensigon/domain/entities/service.py
dimensigon/domain/entities/software.py
dimensigon/domain/entities/step.py
dimensigon/domain/entities/transfer.py
dimensigon/domain/entities/user.py
dimensigon/domain/entities/vault.py
dimensigon/dshell/__init__.py
dimensigon/dshell/argparse_raise.py
dimensigon/dshell/bootstrap.py
dimensigon/dshell/commands.py
dimensigon/dshell/completer.py
dimensigon/dshell/converters.py
dimensigon/dshell/environ.py
dimensigon/dshell/helpers.py
dimensigon/dshell/history.py
dimensigon/dshell/interactive.py
dimensigon/dshell/network.py
dimensigon/dshell/output.py
dimensigon/dshell/utils.py
dimensigon/dshell/validators.py
dimensigon/dshell/view_path_mapping.py
dimensigon/dshell/batch/__init__.py
dimensigon/dshell/batch/dshell.py
dimensigon/dshell/batch/dshell_action.py
dimensigon/dshell/batch/dshell_orch.py
dimensigon/dshell/prompts/__init__.py
dimensigon/dshell/prompts/action_template.py
dimensigon/dshell/prompts/command.py
dimensigon/dshell/prompts/orchestration.py
dimensigon/dshell/prompts/step.py
dimensigon/dshell/prompts/utils.py
dimensigon/network/__init__.py
dimensigon/network/auth.py
dimensigon-0.3.5.dist-info/LICENSE
dimensigon-0.3.5.dist-info/METADATA
dimensigon-0.3.5.dist-info/WHEEL
dimensigon-0.3.5.dist-info/entry_points.txt
dimensigon-0.3.5.dist-info/top_level.txt
dimensigon-0.3.5.dist-info/RECORD
